bio_grumpy-1.1.3.dist-info/METADATA
bio_grumpy-1.1.3.dist-info/WHEEL
bio_grumpy-1.1.3.dist-info/licenses/LICENSE
grumpy/__init__.py
grumpy/grumpy.pypy310-pp73-arm-linux-gnu.so
grumpy.libs/libgcc_s-262c4f60.so.1
bio_grumpy-1.1.3.dist-info/RECORD
