Metadata-Version: 2.4
Name: bio-grumpy
Version: 1.1.3
Classifier: Development Status :: 5 - Production/Stable
Classifier: Programming Language :: Rust
Classifier: Programming Language :: Python :: Implementation :: CPython
Classifier: Programming Language :: Python :: Implementation :: PyPy
Classifier: Intended Audience :: Science/Research
Classifier: Intended Audience :: Healthcare Industry
Classifier: License :: Other/Proprietary License
License-File: LICENSE
Summary: gumpy re-implemented in Rust
Author-email: Jeremy Westhead <jeremy.westhead@ndm.ox.ac.uk>
License-Expression: University of Oxford, see license file for details.
Requires-Python: >=3.8, <3.13
Project-URL: Source, https://github.com/oxfordmmm/grumpy
